autopyinput/__init__.py
autopyinput/utils.py
autopyinput/word_complete.py
auto_py_input-0.0.1.dist-info/LICENSE
auto_py_input-0.0.1.dist-info/METADATA
auto_py_input-0.0.1.dist-info/WHEEL
auto_py_input-0.0.1.dist-info/top_level.txt
auto_py_input-0.0.1.dist-info/RECORD
