Metadata-Version: 2.1
Name: auto-py-input
Version: 0.0.1
Summary: Input autocompletion
Author-email: Siddhanth_78 <siddhanth.lalgowdar@gmail.com>
Project-URL: Homepage, https://github.com/siddhanth78/autopyinput
Classifier: Programming Language :: Python :: 3
Classifier: License :: OSI Approved :: MIT License
Classifier: Operating System :: Microsoft
Requires-Python: >=3.10
License-File: LICENSE
